layered-0.1.8.dist-info/top_level.txt
layered-0.1.8.dist-info/DESCRIPTION.rst
layered-0.1.8.dist-info/entry_points.txt
layered-0.1.8.dist-info/METADATA
layered-0.1.8.dist-info/WHEEL
layered-0.1.8.dist-info/metadata.json
layered-0.1.8.dist-info/RECORD
layered/utility.py
layered/optimization.py
layered/network.py
layered/cost.py
layered/trainer.py
layered/dataset.py
layered/example.py
layered/activation.py
layered/plot.py
layered/evaluation.py
layered/__init__.py
layered/__main__.py
layered/problem.py
layered/gradient.py
