Metadata-Version: 2.0
Name: layered
Version: 0.1.8
Summary: Clean reference implementation of feed forward neural networks
Home-page: http://github.com/danijar/layered
Author: Danijar Hafner
Author-email: mail@danijar.com
License: MIT
Platform: UNKNOWN
Requires-Dist: PyYAML
Requires-Dist: numpy
Requires-Dist: matplotlib
